{
    "Ambiente":2,
    "Resolucion":{
        "NumeroResolucion":2147483647,
        "FechaInicio":"2024-02-05",
        "FechaFinal":"2025-02-05",
        "Prefijo":"FVCS",
        "NumeroInicial":1,
        "NumeroFinal":10000,
        "ClaveTecnica":"thtdEqNQPCyVbVgo"
        },
    "Factura":"FVCS23",
    "Fecha":"2024-11-06",
    "Hora":"08:49:25",
    "Observacion":"Observacion",
    "FormaDePago":"1",
    "MedioDePago":10,
    "FechaVencimiento":"2024-11-06",
    "CantidadArticulos":2,
    "Cliente":{
        "TipoPersona":2,
        "NombreTipoPersona":"Persona Natural",
        "TipoDocumento":13,
        "NombreTipoDocumento":"Cédula de ciudadanía ",
        "Documento":222222222222,
        "Dv":6,
        "NombreComercial":"Consumidor final ",
        "RazonSocial":"Consumidor final ",
        "Telefono":"3219155489",
        "Correo":"gersonlvargas.na@gmail.com",
        "Departamento":{
            "Codigo":11,
            "Nombre":"Bogota"
            },
        "Ciudad":{
            "Codigo":11001,
            "Nombre":"Bogota, DC."
            },
        "Direccion":"Cra. 69 Bis #37b-64 sur",
        "ResponsabilidadFiscal":"R-99-PN",
        "DetallesTributario":{
            "Codigo":"01",
            "Nombre":"IVA"
        }},
    "Articulos":[{
        "CodigoInterno":40,
        "Nombre":"Producto prueba 5",
        "Cantidad":1,
        "PrecioUnitario":1255,
        "Total":1054.6218487394958,
        "Regalo":"false",
        "DescuentoYRecargos":[],
        "Impuestos":{
            "IVA":{
                "Codigo":"01",
                "Total":200.37815126050418,
                "porcentajes":[{
                    "porcentaje":19,
                    "Base":1054.6218487394958,
                    "Total":200.37815126050418
                    }
                ]}
            }},{
        "CodigoInterno":56,
        "Nombre":"producto de sivar",
        "Cantidad":1,
        "PrecioUnitario":1000,
        "Total":840.3361344537816,
        "Regalo":"false",
        "DescuentoYRecargos":[],
        "Impuestos":{
            "IVA":{
                "Codigo":"01",
                "Total":159.6638655462184,
                "porcentajes":[{
                    "porcentaje":19,
                    "Base":840.3361344537816,
                    "Total":159.6638655462184
                    }]
                    }
        }}],
    "Totales":{
        "Bruto":1894.9579831932774,
        "BaseImpuestos":1894.9579831932774,
        "Descuentos":0,
        "Cargos":0,
        "APagar":2255,
        "Impuestos":428.45},
    "Impuestos":{
        "IVA":{
            "Codigo":"01",
            "porcentajes":[{
                "porcentaje":19,
                "Base":840.3361344537816,
                "Total":159.6638655462184}],
        "Total":2255}}}